cf_submit/__init__.py
cf_submit/cf_colors.py
cf_submit/cf_contests.py
cf_submit/cf_groups.py
cf_submit/cf_gyms.py
cf_submit/cf_hack.py
cf_submit/cf_login.py
cf_submit/cf_main.py
cf_submit/cf_parse.py
cf_submit/cf_problems.py
cf_submit/cf_standings.py
cf_submit/cf_submit.py
cf_submit/cf_test.py
cf_submit/cf_utils.py
cf_submit/codeforces.py
cf_submit/bash_completion/cf
cf_submit/bin/cf_checker
cf_submit-1.4.0.data/scripts/cf
cf_submit-1.4.0.dist-info/LICENSE
cf_submit-1.4.0.dist-info/METADATA
cf_submit-1.4.0.dist-info/WHEEL
cf_submit-1.4.0.dist-info/top_level.txt
cf_submit-1.4.0.dist-info/RECORD
