Metadata-Version: 2.1
Name: cf-submit
Version: 1.4.0
Summary: Submit Codeforces codes via terminal and other coll stuff
Home-page: https://github.com/bacali95/cf_submit
Author: Nasreddine Bac Ali
Author-email: nasreddine.bacali95@gmail.com
License: UNKNOWN
Platform: UNKNOWN
Classifier: Programming Language :: Python :: 3
Classifier: License :: OSI Approved :: MIT License
Classifier: Operating System :: OS Independent
Requires-Dist: Werkzeug (<1.0,>=0.16)
Requires-Dist: lxml
Requires-Dist: prettytable
Requires-Dist: requests
Requires-Dist: robobrowser
